{
  "Compingo": {
    "line_nr": 2,
    "text": "Will you dine with me to-morrow, will call on you at ---"
  },
  "Compitum": {
    "line_nr": 5,
    "text": "Will you dine with me to-morrow, and call for me at ---"
  },
  "Complano": {
    "line_nr": 6,
    "text": "Will you dine with me on Monday at ---"
  },
  "Complico": {
    "line_nr": 7,
    "text": "Will you dine with me on Tuesday at ---"
  },
  "Compos": {
    "line_nr": 8,
    "text": "Will you dine with me on Wednesday at ---"
  },
  "Comprimo": {
    "line_nr": 9,
    "text": "Will you dine with me on Thursday at ---"
  },
  "Comptus": {
    "line_nr": 10,
    "text": "Will you dine with me on Friday at ---"
  },
  "Concivi": {
    "line_nr": 11,
    "text": "Will you dine with me on Saturday at ---"
  },
  "Conclamo": {
    "line_nr": 12,
    "text": "Will you dine with me on Sunday at ---"
  },
  "Concluse": {
    "line_nr": 13,
    "text": "Will you dine with me on the ---"
  },
  "Concolor": {
    "line_nr": 14,
    "text": "Directions have been given"
  },
  "Concoquo": {
    "line_nr": 15,
    "text": "What directions have been given"
  },
  "Conculco": {
    "line_nr": 16,
    "text": "Disbursements amount to ---"
  },
  "Concumbo": {
    "line_nr": 17,
    "text": "Send full account of disbursements"
  },
  "Condemno": {
    "line_nr": 18,
    "text": "What do disbursements amount to"
  },
  "Condoleo": {
    "line_nr": 20,
    "text": "Dispose of it as you please"
  },
  "Condris": {
    "line_nr": 21,
    "text": "Please hold at disposal of ---"
  },
  "Conduxi": {
    "line_nr": 22,
    "text": "Would they be disposed to ---"
  },
  "Condylus": {
    "line_nr": 23,
    "text": "Dispute has arisen between ---"
  },
  "Confero": {
    "line_nr": 24,
    "text": "There is no dispute"
  },
  "Confisus": {
    "line_nr": 25,
    "text": "What is the cause of the dispute"
  },
  "Conformo": {
    "line_nr": 26,
    "text": "What is the distance"
  },
  "Confusus": {
    "line_nr": 27,
    "text": "Do as you propose"
  },
  "Congelo": {
    "line_nr": 28,
    "text": "Do as you think best"
  },
  "Congeries": {
    "line_nr": 29,
    "text": "Do your utmost for our joint benefit"
  },
  "Congius": {
    "line_nr": 30,
    "text": "Do your utmost in the matter"
  }
}
