{
  "Occento": {
    "line_nr": 1,
    "text": "What is owing from ---"
  },
  "Occentus": {
    "line_nr": 2,
    "text": "What is owing to ---"
  },
  "Occiduus": {
    "line_nr": 3,
    "text": "Has been paid"
  },
  "Occiput": {
    "line_nr": 4,
    "text": "Has it been paid"
  },
  "Occisor": {
    "line_nr": 5,
    "text": "Has not been paid"
  },
  "Occludo": {
    "line_nr": 6,
    "text": "Have you paid"
  },
  "Occulco": {
    "line_nr": 7,
    "text": "Must not be paid"
  },
  "Occurro": {
    "line_nr": 8,
    "text": "Will be paid"
  },
  "Oceanus": {
    "line_nr": 9,
    "text": "Will not be paid"
  },
  "Ocellus": {
    "line_nr": 11,
    "text": "Parcel has been forwarded"
  },
  "Ochra": {
    "line_nr": 12,
    "text": "Parcel is waiting remittance"
  },
  "Ocimum": {
    "line_nr": 14,
    "text": "Parcel must be forwarded by passenger train"
  },
  "Ocrea": {
    "line_nr": 15,
    "text": "Parcel received all right"
  },
  "Octans": {
    "line_nr": 16,
    "text": "Have not received the parcel"
  },
  "Octipes": {
    "line_nr": 17,
    "text": "Have you received the parcel"
  },
  "Octogeni": {
    "line_nr": 18,
    "text": "How was the parcel forwarded"
  },
  "Octuplus": {
    "line_nr": 19,
    "text": "When was the parcel forwarded"
  },
  "Octussis": {
    "line_nr": 22,
    "text": "Passage paid here, call for particulars and tickets at ---"
  },
  "Odeum": {
    "line_nr": 24,
    "text": "Passage paid here, telegraph departure, call for particulars at ---"
  },
  "Odi": {
    "line_nr": 25,
    "text": "Take passage by the ---"
  },
  "Odiosum": {
    "line_nr": 27,
    "text": "Take passage, by the and telegraph departure ---"
  },
  "Odor": {
    "line_nr": 28,
    "text": "Take passage, and come at once by the ---"
  },
  "Odoratio": {
    "line_nr": 30,
    "text": "Take passage, and come at once, telegraph departure ---"
  },
  "Odoratus": {
    "line_nr": 31,
    "text": "Patterns are suitable"
  },
  "Odyssea": {
    "line_nr": 32,
    "text": "Patterns are suitable, but material too cheap"
  }
}
