{
  "Persisto": {
    "line_nr": 1,
    "text": "has gone to ---"
  },
  "Perspexi": {
    "line_nr": 2,
    "text": "Am told this is a good thing for ---"
  },
  "Persuasi": {
    "line_nr": 3,
    "text": "--- is good"
  },
  "Persulto": {
    "line_nr": 4,
    "text": "Hedge quickly all you have against ---"
  },
  "Pertendo": {
    "line_nr": 5,
    "text": "Hedge quickly all you have on ---"
  },
  "Pertexo": {
    "line_nr": 6,
    "text": "--- has cracked heel"
  },
  "Pertinax": {
    "line_nr": 7,
    "text": "--- has been sent home"
  },
  "Pervinco": {
    "line_nr": 8,
    "text": "--- will be knocked out"
  },
  "Pervius": {
    "line_nr": 9,
    "text": "Do you know anything for ---"
  },
  "Pestifer": {
    "line_nr": 10,
    "text": "--- dead-lame after exercise"
  },
  "Petalium": {
    "line_nr": 11,
    "text": "--- is lame"
  },
  "Petaso": {
    "line_nr": 12,
    "text": "--- is reported lame"
  },
  "Petiolus": {
    "line_nr": 13,
    "text": "Lay the odds to £5 against ---"
  },
  "Pexatus": {
    "line_nr": 14,
    "text": "Lay the odds to £10 against ---"
  },
  "Phani": {
    "line_nr": 15,
    "text": "Lay the odds to £15 against ---"
  },
  "Phaselus": {
    "line_nr": 16,
    "text": "Lay the odds to £20 against ---"
  },
  "Phasma": {
    "line_nr": 17,
    "text": "Lay the odds to £25 against ---"
  },
  "Phellos": {
    "line_nr": 18,
    "text": "Lay the odds to £30 against ---"
  },
  "Phiditia": {
    "line_nr": 19,
    "text": "Lay the odds to £35 against ---"
  },
  "Phormion": {
    "line_nr": 20,
    "text": "Lay the odds to £40 against ---"
  },
  "Phragmis": {
    "line_nr": 21,
    "text": "Lay the odds to £45 against ---"
  },
  "Phycos": {
    "line_nr": 22,
    "text": "Lay the odds to £50 against ---"
  },
  "Phylaca": {
    "line_nr": 23,
    "text": "Lay the odds to £55 against ---"
  },
  "Phyllon": {
    "line_nr": 24,
    "text": "Lay the odds to £60 against ---"
  },
  "Physema": {
    "line_nr": 25,
    "text": "Lay the odds to £70 against ---"
  },
  "Piaculum": {
    "line_nr": 26,
    "text": "Lay the odds to £80 against ---"
  },
  "Pignero": {
    "line_nr": 27,
    "text": "Lay the odds to £90 against ---"
  },
  "Pigritia": {
    "line_nr": 28,
    "text": "Lay the odds to £100 against ---"
  },
  "Pinaster": {
    "line_nr": 29,
    "text": "Lay the odds to £150 against ---"
  },
  "Pineta": {
    "line_nr": 30,
    "text": "Lay the odds to £200 against ---"
  },
  "Pistacia": {
    "line_nr": 31,
    "text": "Lay the odds to £250 against ---"
  },
  "Pityusa": {
    "line_nr": 32,
    "text": "Lay the odds to £300 against ---"
  },
  "Placenta": {
    "line_nr": 33,
    "text": "Lay the odds to £400 against ---"
  },
  "Placidus": {
    "line_nr": 34,
    "text": "Lay the odds to £500 against ---"
  },
  "Plagiger": {
    "line_nr": 35,
    "text": "Lay the odds to £600 against ---"
  },
  "Plagosus": {
    "line_nr": 36,
    "text": "Lay the odds to £700 against ---"
  }
}
